geodatasim/__init__.py
geodatasim/version.py
geodatasim/analysis/__init__.py
geodatasim/analysis/batch.py
geodatasim/analysis/export.py
geodatasim/analysis/rankings.py
geodatasim/api/__init__.py
geodatasim/api/airports.py
geodatasim/api/openweather.py
geodatasim/api/worldbank.py
geodatasim/core/__init__.py
geodatasim/core/city.py
geodatasim/core/config.py
geodatasim/core/updater.py
geodatasim/core/validator.py
geodatasim/data/__init__.py
geodatasim/data/static.py
geodatasim/ml/__init__.py
geodatasim/ml/clustering.py
geodatasim/ml/similarity.py
geodatasim/models/__init__.py
geodatasim/models/geographic.py
geodatasim/models/indicators.py
geodatasim/utils/__init__.py
geodatasim/utils/cache.py
geodatasim/utils/distance.py
geodatasim/utils/similarity.py
geodatasim/viz/__init__.py
geodatasim/viz/charts.py
geodatasim-0.3.2.dist-info/licenses/LICENSE
geodatasim-0.3.2.dist-info/METADATA
geodatasim-0.3.2.dist-info/WHEEL
geodatasim-0.3.2.dist-info/top_level.txt
geodatasim-0.3.2.dist-info/RECORD
