Metadata-Version: 2.4
Name: geodatasim
Version: 0.3.2
Summary: Geographic + Socioeconomic + Climate intelligence with ML, auto-update, and visualization - World's most comprehensive city data platform
Author-email: Teyfik OZ <teyfikoz@example.com>
License: MIT
Project-URL: Homepage, https://github.com/teyfikoz/GeoDataSim
Project-URL: Repository, https://github.com/teyfikoz/GeoDataSim
Project-URL: Documentation, https://github.com/teyfikoz/GeoDataSim/docs
Project-URL: Issues, https://github.com/teyfikoz/GeoDataSim/issues
Keywords: geography,geospatial,city-data,socioeconomic,climate,world-bank,urban-planning,data-science,gis,location-intelligence,machine-learning,clustering,visualization,plotly,sklearn,auto-update,city-analytics
Classifier: Development Status :: 3 - Alpha
Classifier: Intended Audience :: Developers
Classifier: Intended Audience :: Science/Research
Classifier: License :: OSI Approved :: MIT License
Classifier: Programming Language :: Python :: 3
Classifier: Programming Language :: Python :: 3.10
Classifier: Programming Language :: Python :: 3.11
Classifier: Programming Language :: Python :: 3.12
Classifier: Topic :: Scientific/Engineering :: GIS
Classifier: Topic :: Scientific/Engineering :: Information Analysis
Classifier: Topic :: Software Development :: Libraries :: Python Modules
Requires-Python: >=3.10
License-File: LICENSE
Requires-Dist: requests>=2.31.0
Requires-Dist: pandas>=2.0.0
Requires-Dist: numpy>=1.24.0
Requires-Dist: python-dateutil>=2.8.0
Requires-Dist: scikit-learn>=1.3.0
Requires-Dist: numba>=0.58.0
Requires-Dist: pydantic>=2.5.0
Requires-Dist: plotly>=5.17.0
Requires-Dist: kaleido>=0.2.1
Requires-Dist: geopy>=2.4.0
Requires-Dist: tqdm>=4.66.0
Provides-Extra: dev
Requires-Dist: pytest>=7.0; extra == "dev"
Requires-Dist: pytest-cov>=4.0; extra == "dev"
Requires-Dist: black>=23.0; extra == "dev"
Requires-Dist: ruff>=0.1.0; extra == "dev"
Requires-Dist: mypy>=1.0; extra == "dev"
Provides-Extra: export
Requires-Dist: openpyxl>=3.1.0; extra == "export"
Requires-Dist: tabulate>=0.9.0; extra == "export"
Provides-Extra: weather
Requires-Dist: pyowm>=3.3.0; extra == "weather"
Provides-Extra: full
Requires-Dist: openpyxl>=3.1.0; extra == "full"
Requires-Dist: tabulate>=0.9.0; extra == "full"
Requires-Dist: pyowm>=3.3.0; extra == "full"
Requires-Dist: geopy>=2.4.0; extra == "full"
Requires-Dist: pycountry>=23.0; extra == "full"
Dynamic: license-file
